{
    "key": "group_68263510e8187",
    "title": "Hero-block",
    "fields": [
        {
            "key": "field_682635112719d",
            "label": "heading",
            "name": "heading",
            "aria-label": "",
            "type": "text",
            "instructions": "",
            "required": 0,
            "conditional_logic": 0,
            "wrapper": {
                "width": "",
                "class": "",
                "id": ""
            },
            "default_value": "",
            "maxlength": "",
            "allow_in_bindings": 0,
            "placeholder": "",
            "prepend": "",
            "append": ""
        },
        {
            "key": "field_683d64f635ee2",
            "label": "description",
            "name": "description",
            "aria-label": "",
            "type": "text",
            "instructions": "",
            "required": 0,
            "conditional_logic": 0,
            "wrapper": {
                "width": "",
                "class": "",
                "id": ""
            },
            "default_value": "",
            "maxlength": "",
            "allow_in_bindings": 0,
            "placeholder": "",
            "prepend": "",
            "append": ""
        }
    ],
    "location": [
        [
            {
                "param": "block",
                "operator": "==",
                "value": "acf\/hero-block"
            }
        ]
    ],
    "menu_order": 0,
    "position": "normal",
    "style": "default",
    "label_placement": "top",
    "instruction_placement": "label",
    "hide_on_screen": "",
    "active": true,
    "description": "",
    "show_in_rest": 0,
    "modified": 1748854032
}
